losh/__init__.py
losh-0.0.0.dist-info/licenses/LICENSE
losh-0.0.0.dist-info/METADATA
losh-0.0.0.dist-info/WHEEL
losh-0.0.0.dist-info/top_level.txt
losh-0.0.0.dist-info/RECORD
