Metadata-Version: 2.4
Name: losh
Version: 0.0.0
Summary: losh package
Home-page: https://github.com/attentionmech/losh
Author: attentionmech
Author-email: attentionmech@example.com
Classifier: Programming Language :: Python :: 3
Classifier: License :: OSI Approved :: MIT License
Classifier: Operating System :: OS Independent
Requires-Python: >=3.6
License-File: LICENSE
Dynamic: author
Dynamic: author-email
Dynamic: classifier
Dynamic: description
Dynamic: description-content-type
Dynamic: home-page
Dynamic: license-file
Dynamic: requires-python
Dynamic: summary
